pypodman/__init__.py
pypodman/core/engine_manager/app_initializer.py
pypodman/core/engine_manager/engine_initializer.py
pypodman/core/engine_manager/swarm_initializer.py
pypodman/core/pod_manager/app_manager.py
pypodman/core/pod_manager/isolaton_manager.py
pypodman/core/pod_manager/pod_manager.py
pypodman/core/pod_manager/service_manager.py
pypodman/core/varible_manager/name_manager.py
pypodman/core/varible_manager/path_manager.py
pypodman/utils/cli.py
pypodman/utils/config_loader.py
pypodman/utils/logger_manager.py
pypodman/utils/thread_manager.py
python_pod_manager-1.0.2.dist-info/LICENSE
python_pod_manager-1.0.2.dist-info/METADATA
python_pod_manager-1.0.2.dist-info/WHEEL
python_pod_manager-1.0.2.dist-info/entry_points.txt
python_pod_manager-1.0.2.dist-info/top_level.txt
python_pod_manager-1.0.2.dist-info/RECORD
