Metadata-Version: 2.1
Name: python-pod-manager
Version: 1.0.2
Summary: A pod manager for version dependency python projects.
Home-page: https://gitlab.com/Hakanbaban53/python-pod-manager
Author: Hakan İSMAİL
Author-email: hakanismail53@gmail.com
License: MIT License
Classifier: Programming Language :: Python :: 3
Classifier: License :: OSI Approved :: MIT License
Classifier: Operating System :: POSIX :: Linux
Classifier: Operating System :: MacOS :: MacOS X
Classifier: Operating System :: POSIX
Requires-Python: >=3.6
License-File: LICENSE
Requires-Dist: pyyaml
Requires-Dist: psutil
Requires-Dist: colorama
